caic/__init__.py
caic/utils/__init__.py
caic/utils/cjson.py
caic/utils/logger.py
caic/utils/utils.py
numalo-0.1.0.dist-info/METADATA
numalo-0.1.0.dist-info/WHEEL
numalo-0.1.0.dist-info/top_level.txt
numalo-0.1.0.dist-info/RECORD
