Metadata-Version: 2.1
Name: numalo
Version: 0.1.0
Summary: This is a caic project package.
Home-page: http://www.cbguo.com
Author: Bangguo Chen
Author-email: mail@cbguo.com
